BETTER_NMA/__init__.py
BETTER_NMA/adversarial_score.py
BETTER_NMA/change_cluster_name.py
BETTER_NMA/detect_attack.py
BETTER_NMA/explaination_score.py
BETTER_NMA/find_lca.py
BETTER_NMA/main.py
BETTER_NMA/nma_creator.py
BETTER_NMA/plot.py
BETTER_NMA/query_image.py
BETTER_NMA/train_adversarial_detector.py
BETTER_NMA/white_box_testing.py
BETTER_NMA/utilss/__init__.py
BETTER_NMA/utilss/models_utils.py
BETTER_NMA/utilss/photos_uitls.py
BETTER_NMA/utilss/photos_utils.py
BETTER_NMA/utilss/verbal_explanation.py
BETTER_NMA/utilss/wordnet_utils.py
BETTER_NMA/utilss/classes/__init__.py
BETTER_NMA/utilss/classes/adversarial_dataset.py
BETTER_NMA/utilss/classes/adversarial_detector.py
BETTER_NMA/utilss/classes/dendrogram.py
BETTER_NMA/utilss/classes/edges_dataframe.py
BETTER_NMA/utilss/classes/score_calculator.py
BETTER_NMA/utilss/classes/whitebox_testing.py
BETTER_NMA/utilss/classes/preprocessing/__init__.py
BETTER_NMA/utilss/classes/preprocessing/batch_predictor.py
BETTER_NMA/utilss/classes/preprocessing/graph_builder.py
BETTER_NMA/utilss/classes/preprocessing/heap_processor.py
BETTER_NMA/utilss/classes/preprocessing/hierarchical_clustering_builder.py
BETTER_NMA/utilss/classes/preprocessing/tree_node.py
BETTER_NMA/utilss/classes/preprocessing/z_builder.py
BETTER_NMA/utilss/enums/__init__.py
BETTER_NMA/utilss/enums/explanation_method.py
BETTER_NMA/utilss/enums/heap_types.py
BETTER_NMA-1.1.1.dist-info/METADATA
BETTER_NMA-1.1.1.dist-info/WHEEL
BETTER_NMA-1.1.1.dist-info/top_level.txt
BETTER_NMA-1.1.1.dist-info/RECORD
